psec/__init__.py
psec/aes.py
psec/cvv.py
psec/des.py
psec/mac.py
psec/pin.py
psec/pinblock.py
psec/py.typed
psec/tools.py
psec/tr31.py
psec-1.3.0.dist-info/LICENSE.md
psec-1.3.0.dist-info/METADATA
psec-1.3.0.dist-info/WHEEL
psec-1.3.0.dist-info/top_level.txt
psec-1.3.0.dist-info/RECORD
