Metadata-Version: 2.1
Name: psec
Version: 1.3.0
Summary: A Python package for cryptography in payment systems
Home-page: https://github.com/knovichikhin/psec
Author: Konstantin Novichikhin
Author-email: konstantin.novichikhin@gmail.com
License: MIT
Keywords: payment security cvv cvd cvc mac iso9797 tdes aes tr31
Platform: UNKNOWN
Classifier: Development Status :: 5 - Production/Stable
Classifier: Intended Audience :: Developers
Classifier: License :: OSI Approved :: MIT License
Classifier: Operating System :: OS Independent
Classifier: Programming Language :: Python
Classifier: Programming Language :: Python :: 3.6
Classifier: Programming Language :: Python :: 3.7
Classifier: Programming Language :: Python :: 3.8
Classifier: Programming Language :: Python :: 3.9
Classifier: Programming Language :: Python :: 3.10
Classifier: Programming Language :: Python :: Implementation :: CPython
Classifier: Programming Language :: Python :: Implementation :: PyPy
Classifier: Topic :: Security :: Cryptography
Classifier: Topic :: Software Development :: Libraries :: Python Modules
Requires-Python: >=3.6
License-File: LICENSE.md
Requires-Dist: cryptography (>=1.0)
